salmon/__init__.py
salmon/building.py
salmon/comparison.py
salmon/expression.py
salmon/model.py
salmon/test.py
salmon/transformation.py
salmon_lm-1.2.dist-info/LICENSE.txt
salmon_lm-1.2.dist-info/METADATA
salmon_lm-1.2.dist-info/WHEEL
salmon_lm-1.2.dist-info/top_level.txt
salmon_lm-1.2.dist-info/RECORD
